{".class": "MypyFile", "_fullname": "pip._vendor.chardet.mbcssm", "is_partial_stub_package": false, "is_stub": false, "names": {".class": "SymbolTable", "BIG5_CHAR_LEN_TABLE": {".class": "SymbolTableNode", "kind": "Gdef", "node": {".class": "Var", "flags": [], "fullname": "pip._vendor.chardet.mbcssm.BIG5_CHAR_LEN_TABLE", "name": "BIG5_CHAR_LEN_TABLE", "type": {".class": "TupleType", "implicit": false, "items": ["builtins.int", "builtins.int", "builtins.int", "builtins.int", "builtins.int"], "partial_fallback": {".class": "Instance", "args": [{".class": "AnyType", "missing_import_name": null, "source_any": null, "type_of_any": 6}], "type_ref": "builtins.tuple"}}}}, "BIG5_CLS": {".class": "SymbolTableNode", "kind": "Gdef", "node": {".class": "Var", "flags": [], "fullname": "pip._vendor.chardet.mbcssm.BIG5_CLS", "name": "BIG5_CLS", "type": {".class": "TupleType", "implicit": false, "items": ["builtins.int", "builtins.int", "builtins.int", "builtins.int", "builtins.int", "builtins.int", "builtins.int", "builtins.int", "builtins.int", "builtins.int", "builtins.int", "builtins.int", "builtins.int", "builtins.int", "builtins.int", "builtins.int", "builtins.int", "builtins.int", "builtins.int", "builtins.int", "builtins.int", "builtins.int", "builtins.int", "builtins.int", "builtins.int", "builtins.int", "builtins.int", "builtins.int", "builtins.int", "builtins.int", "builtins.int", "builtins.int", "builtins.int", "builtins.int", "builtins.int", "builtins.int", "builtins.int", "builtins.int", "builtins.int", "builtins.int", "builtins.int", "builtins.int", "builtins.int", "builtins.int", "builtins.int", "builtins.int", "builtins.int", "builtins.int", "builtins.int", "builtins.int", "builtins.int", "builtins.int", "builtins.int", "builtins.int", "builtins.int", "builtins.int", "builtins.int", "builtins.int", "builtins.int", "builtins.int", "builtins.int", "builtins.int", "builtins.int", "builtins.int", "builtins.int", "builtins.int", "builtins.int", "builtins.int", "builtins.int", "builtins.int", "builtins.int", "builtins.int", "builtins.int", "builtins.int", "builtins.int", "builtins.int", "builtins.int", "builtins.int", "builtins.int", "builtins.int", "builtins.int", "builtins.int", "builtins.int", "builtins.int", "builtins.int", "builtins.int", "builtins.int", "builtins.int", "builtins.int", "builtins.int", "builtins.int", "builtins.int", "builtins.int", "builtins.int", "builtins.int", "builtins.int", "builtins.int", "builtins.int", "builtins.int", "builtins.int", "builtins.int", "builtins.int", "builtins.int", "builtins.int", "builtins.int", "builtins.int", "builtins.int", "builtins.int", "builtins.int", "builtins.int", "builtins.int", "builtins.int", "builtins.int", "builtins.int", "builtins.int", "builtins.int", "builtins.int", "builtins.int", "builtins.int", "builtins.int", "builtins.int", "builtins.int", "builtins.int", "builtins.int", "builtins.int", "builtins.int", "builtins.int", "builtins.int", "builtins.int", "builtins.int", "builtins.int", "builtins.int", "builtins.int", "builtins.int", "builtins.int", "builtins.int", "builtins.int", "builtins.int", "builtins.int", "builtins.int", "builtins.int", "builtins.int", "builtins.int", "builtins.int", "builtins.int", "builtins.int", "builtins.int", "builtins.int", "builtins.int", "builtins.int", "builtins.int", "builtins.int", "builtins.int", "builtins.int", "builtins.int", "builtins.int", "builtins.int", "builtins.int", "builtins.int", "builtins.int", "builtins.int", "builtins.int", "builtins.int", "builtins.int", "builtins.int", "builtins.int", "builtins.int", "builtins.int", "builtins.int", "builtins.int", "builtins.int", "builtins.int", "builtins.int", "builtins.int", "builtins.int", "builtins.int", "builtins.int", "builtins.int", "builtins.int", "builtins.int", "builtins.int", "builtins.int", "builtins.int", "builtins.int", "builtins.int", "builtins.int", "builtins.int", "builtins.int", "builtins.int", "builtins.int", "builtins.int", "builtins.int", "builtins.int", "builtins.int", "builtins.int", "builtins.int", "builtins.int", "builtins.int", "builtins.int", "builtins.int", "builtins.int", "builtins.int", "builtins.int", "builtins.int", "builtins.int", "builtins.int", "builtins.int", "builtins.int", "builtins.int", "builtins.int", "builtins.int", "builtins.int", "builtins.int", "builtins.int", "builtins.int", "builtins.int", "builtins.int", "builtins.int", "builtins.int", "builtins.int", "builtins.int", "builtins.int", "builtins.int", "builtins.int", "builtins.int", "builtins.int", "builtins.int", "builtins.int", "builtins.int", "builtins.int", "builtins.int", "builtins.int", "builtins.int", "builtins.int", "builtins.int", "builtins.int", "builtins.int", "builtins.int", "builtins.int", "builtins.int", "builtins.int", "builtins.int", "builtins.int", "builtins.int", "builtins.int", "builtins.int", "builtins.int", "builtins.int", "builtins.int", "builtins.int", "builtins.int", "builtins.int", "builtins.int", "builtins.int", "builtins.int", "builtins.int"], "partial_fallback": {".class": "Instance", "args": [{".class": "AnyType", "missing_import_name": null, "source_any": null, "type_of_any": 6}], "type_ref": "builtins.tuple"}}}}, "BIG5_SM_MODEL": {".class": "SymbolTableNode", "kind": "Gdef", "node": {".class": "Var", "flags": [], "fullname": "pip._vendor.chardet.mbcssm.BIG5_SM_MODEL", "name": "BIG5_SM_MODEL", "type": {".class": "Instance", "args": ["builtins.str", "builtins.object"], "type_ref": "builtins.dict"}}}, "BIG5_ST": {".class": "SymbolTableNode", "kind": "Gdef", "node": {".class": "Var", "flags": [], "fullname": "pip._vendor.chardet.mbcssm.BIG5_ST", "name": "BIG5_ST", "type": {".class": "TupleType", "implicit": false, "items": ["builtins.int", "builtins.int", "builtins.int", "builtins.int", "builtins.int", "builtins.int", "builtins.int", "builtins.int", "builtins.int", "builtins.int", "builtins.int", "builtins.int", "builtins.int", "builtins.int", "builtins.int", "builtins.int", "builtins.int", "builtins.int", "builtins.int", "builtins.int", "builtins.int", "builtins.int", "builtins.int", "builtins.int"], "partial_fallback": {".class": "Instance", "args": [{".class": "AnyType", "missing_import_name": null, "source_any": null, "type_of_any": 6}], "type_ref": "builtins.tuple"}}}}, "CP949_CHAR_LEN_TABLE": {".class": "SymbolTableNode", "kind": "Gdef", "node": {".class": "Var", "flags": [], "fullname": "pip._vendor.chardet.mbcssm.CP949_CHAR_LEN_TABLE", "name": "CP949_CHAR_LEN_TABLE", "type": {".class": "TupleType", "implicit": false, "items": ["builtins.int", "builtins.int", "builtins.int", "builtins.int", "builtins.int", "builtins.int", "builtins.int", "builtins.int", "builtins.int", "builtins.int"], "partial_fallback": {".class": "Instance", "args": [{".class": "AnyType", "missing_import_name": null, "source_any": null, "type_of_any": 6}], "type_ref": "builtins.tuple"}}}}, "CP949_CLS": {".class": "SymbolTableNode", "kind": "Gdef", "node": {".class": "Var", "flags": [], "fullname": "pip._vendor.chardet.mbcssm.CP949_CLS", "name": "CP949_CLS", "type": {".class": "TupleType", "implicit": false, "items": ["builtins.int", "builtins.int", "builtins.int", "builtins.int", "builtins.int", "builtins.int", "builtins.int", "builtins.int", "builtins.int", "builtins.int", "builtins.int", "builtins.int", "builtins.int", "builtins.int", "builtins.int", "builtins.int", "builtins.int", "builtins.int", "builtins.int", "builtins.int", "builtins.int", "builtins.int", "builtins.int", "builtins.int", "builtins.int", "builtins.int", "builtins.int", "builtins.int", "builtins.int", "builtins.int", "builtins.int", "builtins.int", "builtins.int", "builtins.int", "builtins.int", "builtins.int", "builtins.int", "builtins.int", "builtins.int", "builtins.int", "builtins.int", "builtins.int", "builtins.int", "builtins.int", "builtins.int", "builtins.int", "builtins.int", "builtins.int", "builtins.int", "builtins.int", "builtins.int", "builtins.int", "builtins.int", "builtins.int", "builtins.int", "builtins.int", "builtins.int", "builtins.int", "builtins.int", "builtins.int", "builtins.int", "builtins.int", "builtins.int", "builtins.int", "builtins.int", "builtins.int", "builtins.int", "builtins.int", "builtins.int", "builtins.int", "builtins.int", "builtins.int", "builtins.int", "builtins.int", "builtins.int", "builtins.int", "builtins.int", "builtins.int", "builtins.int", "builtins.int", "builtins.int", "builtins.int", "builtins.int", "builtins.int", "builtins.int", "builtins.int", "builtins.int", "builtins.int", "builtins.int", "builtins.int", "builtins.int", "builtins.int", "builtins.int", "builtins.int", "builtins.int", "builtins.int", "builtins.int", "builtins.int", "builtins.int", "builtins.int", "builtins.int", "builtins.int", "builtins.int", "builtins.int", "builtins.int", "builtins.int", "builtins.int", "builtins.int", "builtins.int", "builtins.int", "builtins.int", "builtins.int", "builtins.int", "builtins.int", "builtins.int", "builtins.int", "builtins.int", "builtins.int", "builtins.int", "builtins.int", "builtins.int", "builtins.int", "builtins.int", "builtins.int", "builtins.int", "builtins.int", "builtins.int", "builtins.int", "builtins.int", "builtins.int", "builtins.int", "builtins.int", "builtins.int", "builtins.int", "builtins.int", "builtins.int", "builtins.int", "builtins.int", "builtins.int", "builtins.int", "builtins.int", "builtins.int", "builtins.int", "builtins.int", "builtins.int", "builtins.int", "builtins.int", "builtins.int", "builtins.int", "builtins.int", "builtins.int", "builtins.int", "builtins.int", "builtins.int", "builtins.int", "builtins.int", "builtins.int", "builtins.int", "builtins.int", "builtins.int", "builtins.int", "builtins.int", "builtins.int", "builtins.int", "builtins.int", "builtins.int", "builtins.int", "builtins.int", "builtins.int", "builtins.int", "builtins.int", "builtins.int", "builtins.int", "builtins.int", "builtins.int", "builtins.int", "builtins.int", "builtins.int", "builtins.int", "builtins.int", "builtins.int", "builtins.int", "builtins.int", "builtins.int", "builtins.int", "builtins.int", "builtins.int", "builtins.int", "builtins.int", "builtins.int", "builtins.int", "builtins.int", "builtins.int", "builtins.int", "builtins.int", "builtins.int", "builtins.int", "builtins.int", "builtins.int", "builtins.int", "builtins.int", "builtins.int", "builtins.int", "builtins.int", "builtins.int", "builtins.int", "builtins.int", "builtins.int", "builtins.int", "builtins.int", "builtins.int", "builtins.int", "builtins.int", "builtins.int", "builtins.int", "builtins.int", "builtins.int", "builtins.int", "builtins.int", "builtins.int", "builtins.int", "builtins.int", "builtins.int", "builtins.int", "builtins.int", "builtins.int", "builtins.int", "builtins.int", "builtins.int", "builtins.int", "builtins.int", "builtins.int", "builtins.int", "builtins.int", "builtins.int", "builtins.int", "builtins.int", "builtins.int", "builtins.int", "builtins.int", "builtins.int", "builtins.int", "builtins.int", "builtins.int", "builtins.int", "builtins.int", "builtins.int", "builtins.int", "builtins.int", "builtins.int", "builtins.int", "builtins.int", "builtins.int", "builtins.int", "builtins.int", "builtins.int"], "partial_fallback": {".class": "Instance", "args": [{".class": "AnyType", "missing_import_name": null, "source_any": null, "type_of_any": 6}], "type_ref": "builtins.tuple"}}}}, "CP949_SM_MODEL": {".class": "SymbolTableNode", "kind": "Gdef", "node": {".class": "Var", "flags": [], "fullname": "pip._vendor.chardet.mbcssm.CP949_SM_MODEL", "name": "CP949_SM_MODEL", "type": {".class": "Instance", "args": ["builtins.str", "builtins.object"], "type_ref": "builtins.dict"}}}, "CP949_ST": {".class": "SymbolTableNode", "kind": "Gdef", "node": {".class": "Var", "flags": [], "fullname": "pip._vendor.chardet.mbcssm.CP949_ST", "name": "CP949_ST", "type": {".class": "TupleType", "implicit": false, "items": ["builtins.int", "builtins.int", "builtins.int", "builtins.int", "builtins.int", "builtins.int", "builtins.int", "builtins.int", "builtins.int", "builtins.int", "builtins.int", "builtins.int", "builtins.int", "builtins.int", "builtins.int", "builtins.int", "builtins.int", "builtins.int", "builtins.int", "builtins.int", "builtins.int", "builtins.int", "builtins.int", "builtins.int", "builtins.int", "builtins.int", "builtins.int", "builtins.int", "builtins.int", "builtins.int", "builtins.int", "builtins.int", "builtins.int", "builtins.int", "builtins.int", "builtins.int", "builtins.int", "builtins.int", "builtins.int", "builtins.int", "builtins.int", "builtins.int", "builtins.int", "builtins.int", "builtins.int", "builtins.int", "builtins.int", "builtins.int", "builtins.int", "builtins.int", "builtins.int", "builtins.int", "builtins.int", "builtins.int", "builtins.int", "builtins.int", "builtins.int", "builtins.int", "builtins.int", "builtins.int", "builtins.int", "builtins.int", "builtins.int", "builtins.int", "builtins.int", "builtins.int", "builtins.int", "builtins.int", "builtins.int", "builtins.int"], "partial_fallback": {".class": "Instance", "args": [{".class": "AnyType", "missing_import_name": null, "source_any": null, "type_of_any": 6}], "type_ref": "builtins.tuple"}}}}, "EUCJP_CHAR_LEN_TABLE": {".class": "SymbolTableNode", "kind": "Gdef", "node": {".class": "Var", "flags": [], "fullname": "pip._vendor.chardet.mbcssm.EUCJP_CHAR_LEN_TABLE", "name": "EUCJP_CHAR_LEN_TABLE", "type": {".class": "TupleType", "implicit": false, "items": ["builtins.int", "builtins.int", "builtins.int", "builtins.int", "builtins.int", "builtins.int"], "partial_fallback": {".class": "Instance", "args": [{".class": "AnyType", "missing_import_name": null, "source_any": null, "type_of_any": 6}], "type_ref": "builtins.tuple"}}}}, "EUCJP_CLS": {".class": "SymbolTableNode", "kind": "Gdef", "node": {".class": "Var", "flags": [], "fullname": "pip._vendor.chardet.mbcssm.EUCJP_CLS", "name": "EUCJP_CLS", "type": {".class": "TupleType", "implicit": false, "items": ["builtins.int", "builtins.int", "builtins.int", "builtins.int", "builtins.int", "builtins.int", "builtins.int", "builtins.int", "builtins.int", "builtins.int", "builtins.int", "builtins.int", "builtins.int", "builtins.int", "builtins.int", "builtins.int", "builtins.int", "builtins.int", "builtins.int", "builtins.int", "builtins.int", "builtins.int", "builtins.int", "builtins.int", "builtins.int", "builtins.int", "builtins.int", "builtins.int", "builtins.int", "builtins.int", "builtins.int", "builtins.int", "builtins.int", "builtins.int", "builtins.int", "builtins.int", "builtins.int", "builtins.int", "builtins.int", "builtins.int", "builtins.int", "builtins.int", "builtins.int", "builtins.int", "builtins.int", "builtins.int", "builtins.int", "builtins.int", "builtins.int", "builtins.int", "builtins.int", "builtins.int", "builtins.int", "builtins.int", "builtins.int", "builtins.int", "builtins.int", "builtins.int", "builtins.int", "builtins.int", "builtins.int", "builtins.int", "builtins.int", "builtins.int", "builtins.int", "builtins.int", "builtins.int", "builtins.int", "builtins.int", "builtins.int", "builtins.int", "builtins.int", "builtins.int", "builtins.int", "builtins.int", "builtins.int", "builtins.int", "builtins.int", "builtins.int", "builtins.int", "builtins.int", "builtins.int", "builtins.int", "builtins.int", "builtins.int", "builtins.int", "builtins.int", "builtins.int", "builtins.int", "builtins.int", "builtins.int", "builtins.int", "builtins.int", "builtins.int", "builtins.int", "builtins.int", "builtins.int", "builtins.int", "builtins.int", "builtins.int", "builtins.int", "builtins.int", "builtins.int", "builtins.int", "builtins.int", "builtins.int", "builtins.int", "builtins.int", "builtins.int", "builtins.int", "builtins.int", "builtins.int", "builtins.int", "builtins.int", "builtins.int", "builtins.int", "builtins.int", "builtins.int", "builtins.int", "builtins.int", "builtins.int", "builtins.int", "builtins.int", "builtins.int", "builtins.int", "builtins.int", "builtins.int", "builtins.int", "builtins.int", "builtins.int", "builtins.int", "builtins.int", "builtins.int", "builtins.int", "builtins.int", "builtins.int", "builtins.int", "builtins.int", "builtins.int", "builtins.int", "builtins.int", "builtins.int", "builtins.int", "builtins.int", "builtins.int", "builtins.int", "builtins.int", "builtins.int", "builtins.int", "builtins.int", "builtins.int", "builtins.int", "builtins.int", "builtins.int", "builtins.int", "builtins.int", "builtins.int", "builtins.int", "builtins.int", "builtins.int", "builtins.int", "builtins.int", "builtins.int", "builtins.int", "builtins.int", "builtins.int", "builtins.int", "builtins.int", "builtins.int", "builtins.int", "builtins.int", "builtins.int", "builtins.int", "builtins.int", "builtins.int", "builtins.int", "builtins.int", "builtins.int", "builtins.int", "builtins.int", "builtins.int", "builtins.int", "builtins.int", "builtins.int", "builtins.int", "builtins.int", "builtins.int", "builtins.int", "builtins.int", "builtins.int", "builtins.int", "builtins.int", "builtins.int", "builtins.int", "builtins.int", "builtins.int", "builtins.int", "builtins.int", "builtins.int", "builtins.int", "builtins.int", "builtins.int", "builtins.int", "builtins.int", "builtins.int", "builtins.int", "builtins.int", "builtins.int", "builtins.int", "builtins.int", "builtins.int", "builtins.int", "builtins.int", "builtins.int", "builtins.int", "builtins.int", "builtins.int", "builtins.int", "builtins.int", "builtins.int", "builtins.int", "builtins.int", "builtins.int", "builtins.int", "builtins.int", "builtins.int", "builtins.int", "builtins.int", "builtins.int", "builtins.int", "builtins.int", "builtins.int", "builtins.int", "builtins.int", "builtins.int", "builtins.int", "builtins.int", "builtins.int", "builtins.int", "builtins.int", "builtins.int", "builtins.int", "builtins.int", "builtins.int", "builtins.int", "builtins.int", "builtins.int", "builtins.int", "builtins.int", "builtins.int", "builtins.int", "builtins.int", "builtins.int", "builtins.int", "builtins.int", "builtins.int"], "partial_fallback": {".class": "Instance", "args": [{".class": "AnyType", "missing_import_name": null, "source_any": null, "type_of_any": 6}], "type_ref": "builtins.tuple"}}}}, "EUCJP_SM_MODEL": {".class": "SymbolTableNode", "kind": "Gdef", "node": {".class": "Var", "flags": [], "fullname": "pip._vendor.chardet.mbcssm.EUCJP_SM_MODEL", "name": "EUCJP_SM_MODEL", "type": {".class": "Instance", "args": ["builtins.str", "builtins.object"], "type_ref": "builtins.dict"}}}, "EUCJP_ST": {".class": "SymbolTableNode", "kind": "Gdef", "node": {".class": "Var", "flags": [], "fullname": "pip._vendor.chardet.mbcssm.EUCJP_ST", "name": "EUCJP_ST", "type": {".class": "TupleType", "implicit": false, "items": ["builtins.int", "builtins.int", "builtins.int", "builtins.int", "builtins.int", "builtins.int", "builtins.int", "builtins.int", "builtins.int", "builtins.int", "builtins.int", "builtins.int", "builtins.int", "builtins.int", "builtins.int", "builtins.int", "builtins.int", "builtins.int", "builtins.int", "builtins.int", "builtins.int", "builtins.int", "builtins.int", "builtins.int", "builtins.int", "builtins.int", "builtins.int", "builtins.int", "builtins.int", "builtins.int", "builtins.int", "builtins.int", "builtins.int", "builtins.int", "builtins.int", "builtins.int", "builtins.int", "builtins.int", "builtins.int", "builtins.int"], "partial_fallback": {".class": "Instance", "args": [{".class": "AnyType", "missing_import_name": null, "source_any": null, "type_of_any": 6}], "type_ref": "builtins.tuple"}}}}, "EUCKR_CHAR_LEN_TABLE": {".class": "SymbolTableNode", "kind": "Gdef", "node": {".class": "Var", "flags": [], "fullname": "pip._vendor.chardet.mbcssm.EUCKR_CHAR_LEN_TABLE", "name": "EUCKR_CHAR_LEN_TABLE", "type": {".class": "TupleType", "implicit": false, "items": ["builtins.int", "builtins.int", "builtins.int", "builtins.int"], "partial_fallback": {".class": "Instance", "args": [{".class": "AnyType", "missing_import_name": null, "source_any": null, "type_of_any": 6}], "type_ref": "builtins.tuple"}}}}, "EUCKR_CLS": {".class": "SymbolTableNode", "kind": "Gdef", "node": {".class": "Var", "flags": [], "fullname": "pip._vendor.chardet.mbcssm.EUCKR_CLS", "name": "EUCKR_CLS", "type": {".class": "TupleType", "implicit": false, "items": ["builtins.int", "builtins.int", "builtins.int", "builtins.int", "builtins.int", "builtins.int", "builtins.int", "builtins.int", "builtins.int", "builtins.int", "builtins.int", "builtins.int", "builtins.int", "builtins.int", "builtins.int", "builtins.int", "builtins.int", "builtins.int", "builtins.int", "builtins.int", "builtins.int", "builtins.int", "builtins.int", "builtins.int", "builtins.int", "builtins.int", "builtins.int", "builtins.int", "builtins.int", "builtins.int", "builtins.int", "builtins.int", "builtins.int", "builtins.int", "builtins.int", "builtins.int", "builtins.int", "builtins.int", "builtins.int", "builtins.int", "builtins.int", "builtins.int", "builtins.int", "builtins.int", "builtins.int", "builtins.int", "builtins.int", "builtins.int", "builtins.int", "builtins.int", "builtins.int", "builtins.int", "builtins.int", "builtins.int", "builtins.int", "builtins.int", "builtins.int", "builtins.int", "builtins.int", "builtins.int", "builtins.int", "builtins.int", "builtins.int", "builtins.int", "builtins.int", "builtins.int", "builtins.int", "builtins.int", "builtins.int", "builtins.int", "builtins.int", "builtins.int", "builtins.int", "builtins.int", "builtins.int", "builtins.int", "builtins.int", "builtins.int", "builtins.int", "builtins.int", "builtins.int", "builtins.int", "builtins.int", "builtins.int", "builtins.int", "builtins.int", "builtins.int", "builtins.int", "builtins.int", "builtins.int", "builtins.int", "builtins.int", "builtins.int", "builtins.int", "builtins.int", "builtins.int", "builtins.int", "builtins.int", "builtins.int", "builtins.int", "builtins.int", "builtins.int", "builtins.int", "builtins.int", "builtins.int", "builtins.int", "builtins.int", "builtins.int", "builtins.int", "builtins.int", "builtins.int", "builtins.int", "builtins.int", "builtins.int", "builtins.int", "builtins.int", "builtins.int", "builtins.int", "builtins.int", "builtins.int", "builtins.int", "builtins.int", "builtins.int", "builtins.int", "builtins.int", "builtins.int", "builtins.int", "builtins.int", "builtins.int", "builtins.int", "builtins.int", "builtins.int", "builtins.int", "builtins.int", "builtins.int", "builtins.int", "builtins.int", "builtins.int", "builtins.int", "builtins.int", "builtins.int", "builtins.int", "builtins.int", "builtins.int", "builtins.int", "builtins.int", "builtins.int", "builtins.int", "builtins.int", "builtins.int", "builtins.int", "builtins.int", "builtins.int", "builtins.int", "builtins.int", "builtins.int", "builtins.int", "builtins.int", "builtins.int", "builtins.int", "builtins.int", "builtins.int", "builtins.int", "builtins.int", "builtins.int", "builtins.int", "builtins.int", "builtins.int", "builtins.int", "builtins.int", "builtins.int", "builtins.int", "builtins.int", "builtins.int", "builtins.int", "builtins.int", "builtins.int", "builtins.int", "builtins.int", "builtins.int", "builtins.int", "builtins.int", "builtins.int", "builtins.int", "builtins.int", "builtins.int", "builtins.int", "builtins.int", "builtins.int", "builtins.int", "builtins.int", "builtins.int", "builtins.int", "builtins.int", "builtins.int", "builtins.int", "builtins.int", "builtins.int", "builtins.int", "builtins.int", "builtins.int", "builtins.int", "builtins.int", "builtins.int", "builtins.int", "builtins.int", "builtins.int", "builtins.int", "builtins.int", "builtins.int", "builtins.int", "builtins.int", "builtins.int", "builtins.int", "builtins.int", "builtins.int", "builtins.int", "builtins.int", "builtins.int", "builtins.int", "builtins.int", "builtins.int", "builtins.int", "builtins.int", "builtins.int", "builtins.int", "builtins.int", "builtins.int", "builtins.int", "builtins.int", "builtins.int", "builtins.int", "builtins.int", "builtins.int", "builtins.int", "builtins.int", "builtins.int", "builtins.int", "builtins.int", "builtins.int", "builtins.int", "builtins.int", "builtins.int", "builtins.int", "builtins.int", "builtins.int", "builtins.int", "builtins.int", "builtins.int", "builtins.int", "builtins.int", "builtins.int", "builtins.int", "builtins.int", "builtins.int", "builtins.int"], "partial_fallback": {".class": "Instance", "args": [{".class": "AnyType", "missing_import_name": null, "source_any": null, "type_of_any": 6}], "type_ref": "builtins.tuple"}}}}, "EUCKR_SM_MODEL": {".class": "SymbolTableNode", "kind": "Gdef", "node": {".class": "Var", "flags": [], "fullname": "pip._vendor.chardet.mbcssm.EUCKR_SM_MODEL", "name": "EUCKR_SM_MODEL", "type": {".class": "Instance", "args": ["builtins.str", "builtins.object"], "type_ref": "builtins.dict"}}}, "EUCKR_ST": {".class": "SymbolTableNode", "kind": "Gdef", "node": {".class": "Var", "flags": [], "fullname": "pip._vendor.chardet.mbcssm.EUCKR_ST", "name": "EUCKR_ST", "type": {".class": "TupleType", "implicit": false, "items": ["builtins.int", "builtins.int", "builtins.int", "builtins.int", "builtins.int", "builtins.int", "builtins.int", "builtins.int", "builtins.int", "builtins.int", "builtins.int", "builtins.int", "builtins.int", "builtins.int", "builtins.int", "builtins.int"], "partial_fallback": {".class": "Instance", "args": [{".class": "AnyType", "missing_import_name": null, "source_any": null, "type_of_any": 6}], "type_ref": "builtins.tuple"}}}}, "EUCTW_CHAR_LEN_TABLE": {".class": "SymbolTableNode", "kind": "Gdef", "node": {".class": "Var", "flags": [], "fullname": "pip._vendor.chardet.mbcssm.EUCTW_CHAR_LEN_TABLE", "name": "EUCTW_CHAR_LEN_TABLE", "type": {".class": "TupleType", "implicit": false, "items": ["builtins.int", "builtins.int", "builtins.int", "builtins.int", "builtins.int", "builtins.int", "builtins.int"], "partial_fallback": {".class": "Instance", "args": [{".class": "AnyType", "missing_import_name": null, "source_any": null, "type_of_any": 6}], "type_ref": "builtins.tuple"}}}}, "EUCTW_CLS": {".class": "SymbolTableNode", "kind": "Gdef", "node": {".class": "Var", "flags": [], "fullname": "pip._vendor.chardet.mbcssm.EUCTW_CLS", "name": "EUCTW_CLS", "type": {".class": "TupleType", "implicit": false, "items": ["builtins.int", "builtins.int", "builtins.int", "builtins.int", "builtins.int", "builtins.int", "builtins.int", "builtins.int", "builtins.int", "builtins.int", "builtins.int", "builtins.int", "builtins.int", "builtins.int", "builtins.int", "builtins.int", "builtins.int", "builtins.int", "builtins.int", "builtins.int", "builtins.int", "builtins.int", "builtins.int", "builtins.int", "builtins.int", "builtins.int", "builtins.int", "builtins.int", "builtins.int", "builtins.int", "builtins.int", "builtins.int", "builtins.int", "builtins.int", "builtins.int", "builtins.int", "builtins.int", "builtins.int", "builtins.int", "builtins.int", "builtins.int", "builtins.int", "builtins.int", "builtins.int", "builtins.int", "builtins.int", "builtins.int", "builtins.int", "builtins.int", "builtins.int", "builtins.int", "builtins.int", "builtins.int", "builtins.int", "builtins.int", "builtins.int", "builtins.int", "builtins.int", "builtins.int", "builtins.int", "builtins.int", "builtins.int", "builtins.int", "builtins.int", "builtins.int", "builtins.int", "builtins.int", "builtins.int", "builtins.int", "builtins.int", "builtins.int", "builtins.int", "builtins.int", "builtins.int", "builtins.int", "builtins.int", "builtins.int", "builtins.int", "builtins.int", "builtins.int", "builtins.int", "builtins.int", "builtins.int", "builtins.int", "builtins.int", "builtins.int", "builtins.int", "builtins.int", "builtins.int", "builtins.int", "builtins.int", "builtins.int", "builtins.int", "builtins.int", "builtins.int", "builtins.int", "builtins.int", "builtins.int", "builtins.int", "builtins.int", "builtins.int", "builtins.int", "builtins.int", "builtins.int", "builtins.int", "builtins.int", "builtins.int", "builtins.int", "builtins.int", "builtins.int", "builtins.int", "builtins.int", "builtins.int", "builtins.int", "builtins.int", "builtins.int", "builtins.int", "builtins.int", "builtins.int", "builtins.int", "builtins.int", "builtins.int", "builtins.int", "builtins.int", "builtins.int", "builtins.int", "builtins.int", "builtins.int", "builtins.int", "builtins.int", "builtins.int", "builtins.int", "builtins.int", "builtins.int", "builtins.int", "builtins.int", "builtins.int", "builtins.int", "builtins.int", "builtins.int", "builtins.int", "builtins.int", "builtins.int", "builtins.int", "builtins.int", "builtins.int", "builtins.int", "builtins.int", "builtins.int", "builtins.int", "builtins.int", "builtins.int", "builtins.int", "builtins.int", "builtins.int", "builtins.int", "builtins.int", "builtins.int", "builtins.int", "builtins.int", "builtins.int", "builtins.int", "builtins.int", "builtins.int", "builtins.int", "builtins.int", "builtins.int", "builtins.int", "builtins.int", "builtins.int", "builtins.int", "builtins.int", "builtins.int", "builtins.int", "builtins.int", "builtins.int", "builtins.int", "builtins.int", "builtins.int", "builtins.int", "builtins.int", "builtins.int", "builtins.int", "builtins.int", "builtins.int", "builtins.int", "builtins.int", "builtins.int", "builtins.int", "builtins.int", "builtins.int", "builtins.int", "builtins.int", "builtins.int", "builtins.int", "builtins.int", "builtins.int", "builtins.int", "builtins.int", "builtins.int", "builtins.int", "builtins.int", "builtins.int", "builtins.int", "builtins.int", "builtins.int", "builtins.int", "builtins.int", "builtins.int", "builtins.int", "builtins.int", "builtins.int", "builtins.int", "builtins.int", "builtins.int", "builtins.int", "builtins.int", "builtins.int", "builtins.int", "builtins.int", "builtins.int", "builtins.int", "builtins.int", "builtins.int", "builtins.int", "builtins.int", "builtins.int", "builtins.int", "builtins.int", "builtins.int", "builtins.int", "builtins.int", "builtins.int", "builtins.int", "builtins.int", "builtins.int", "builtins.int", "builtins.int", "builtins.int", "builtins.int", "builtins.int", "builtins.int", "builtins.int", "builtins.int", "builtins.int", "builtins.int", "builtins.int", "builtins.int", "builtins.int", "builtins.int", "builtins.int", "builtins.int", "builtins.int", "builtins.int", "builtins.int", "builtins.int"], "partial_fallback": {".class": "Instance", "args": [{".class": "AnyType", "missing_import_name": null, "source_any": null, "type_of_any": 6}], "type_ref": "builtins.tuple"}}}}, "EUCTW_SM_MODEL": {".class": "SymbolTableNode", "kind": "Gdef", "node": {".class": "Var", "flags": [], "fullname": "pip._vendor.chardet.mbcssm.EUCTW_SM_MODEL", "name": "EUCTW_SM_MODEL", "type": {".class": "Instance", "args": ["builtins.str", "builtins.object"], "type_ref": "builtins.dict"}}}, "EUCTW_ST": {".class": "SymbolTableNode", "kind": "Gdef", "node": {".class": "Var", "flags": [], "fullname": "pip._vendor.chardet.mbcssm.EUCTW_ST", "name": "EUCTW_ST", "type": {".class": "TupleType", "implicit": false, "items": ["builtins.int", "builtins.int", "builtins.int", "builtins.int", "builtins.int", "builtins.int", "builtins.int", "builtins.int", "builtins.int", "builtins.int", "builtins.int", "builtins.int", "builtins.int", "builtins.int", "builtins.int", "builtins.int", "builtins.int", "builtins.int", "builtins.int", "builtins.int", "builtins.int", "builtins.int", "builtins.int", "builtins.int", "builtins.int", "builtins.int", "builtins.int", "builtins.int", "builtins.int", "builtins.int", "builtins.int", "builtins.int", "builtins.int", "builtins.int", "builtins.int", "builtins.int", "builtins.int", "builtins.int", "builtins.int", "builtins.int", "builtins.int", "builtins.int", "builtins.int", "builtins.int", "builtins.int", "builtins.int", "builtins.int", "builtins.int"], "partial_fallback": {".class": "Instance", "args": [{".class": "AnyType", "missing_import_name": null, "source_any": null, "type_of_any": 6}], "type_ref": "builtins.tuple"}}}}, "GB2312_CHAR_LEN_TABLE": {".class": "SymbolTableNode", "kind": "Gdef", "node": {".class": "Var", "flags": [], "fullname": "pip._vendor.chardet.mbcssm.GB2312_CHAR_LEN_TABLE", "name": "GB2312_CHAR_LEN_TABLE", "type": {".class": "TupleType", "implicit": false, "items": ["builtins.int", "builtins.int", "builtins.int", "builtins.int", "builtins.int", "builtins.int", "builtins.int"], "partial_fallback": {".class": "Instance", "args": [{".class": "AnyType", "missing_import_name": null, "source_any": null, "type_of_any": 6}], "type_ref": "builtins.tuple"}}}}, "GB2312_CLS": {".class": "SymbolTableNode", "kind": "Gdef", "node": {".class": "Var", "flags": [], "fullname": "pip._vendor.chardet.mbcssm.GB2312_CLS", "name": "GB2312_CLS", "type": {".class": "TupleType", "implicit": false, "items": ["builtins.int", "builtins.int", "builtins.int", "builtins.int", "builtins.int", "builtins.int", "builtins.int", "builtins.int", "builtins.int", "builtins.int", "builtins.int", "builtins.int", "builtins.int", "builtins.int", "builtins.int", "builtins.int", "builtins.int", "builtins.int", "builtins.int", "builtins.int", "builtins.int", "builtins.int", "builtins.int", "builtins.int", "builtins.int", "builtins.int", "builtins.int", "builtins.int", "builtins.int", "builtins.int", "builtins.int", "builtins.int", "builtins.int", "builtins.int", "builtins.int", "builtins.int", "builtins.int", "builtins.int", "builtins.int", "builtins.int", "builtins.int", "builtins.int", "builtins.int", "builtins.int", "builtins.int", "builtins.int", "builtins.int", "builtins.int", "builtins.int", "builtins.int", "builtins.int", "builtins.int", "builtins.int", "builtins.int", "builtins.int", "builtins.int", "builtins.int", "builtins.int", "builtins.int", "builtins.int", "builtins.int", "builtins.int", "builtins.int", "builtins.int", "builtins.int", "builtins.int", "builtins.int", "builtins.int", "builtins.int", "builtins.int", "builtins.int", "builtins.int", "builtins.int", "builtins.int", "builtins.int", "builtins.int", "builtins.int", "builtins.int", "builtins.int", "builtins.int", "builtins.int", "builtins.int", "builtins.int", "builtins.int", "builtins.int", "builtins.int", "builtins.int", "builtins.int", "builtins.int", "builtins.int", "builtins.int", "builtins.int", "builtins.int", "builtins.int", "builtins.int", "builtins.int", "builtins.int", "builtins.int", "builtins.int", "builtins.int", "builtins.int", "builtins.int", "builtins.int", "builtins.int", "builtins.int", "builtins.int", "builtins.int", "builtins.int", "builtins.int", "builtins.int", "builtins.int", "builtins.int", "builtins.int", "builtins.int", "builtins.int", "builtins.int", "builtins.int", "builtins.int", "builtins.int", "builtins.int", "builtins.int", "builtins.int", "builtins.int", "builtins.int", "builtins.int", "builtins.int", "builtins.int", "builtins.int", "builtins.int", "builtins.int", "builtins.int", "builtins.int", "builtins.int", "builtins.int", "builtins.int", "builtins.int", "builtins.int", "builtins.int", "builtins.int", "builtins.int", "builtins.int", "builtins.int", "builtins.int", "builtins.int", "builtins.int", "builtins.int", "builtins.int", "builtins.int", "builtins.int", "builtins.int", "builtins.int", "builtins.int", "builtins.int", "builtins.int", "builtins.int", "builtins.int", "builtins.int", "builtins.int", "builtins.int", "builtins.int", "builtins.int", "builtins.int", "builtins.int", "builtins.int", "builtins.int", "builtins.int", "builtins.int", "builtins.int", "builtins.int", "builtins.int", "builtins.int", "builtins.int", "builtins.int", "builtins.int", "builtins.int", "builtins.int", "builtins.int", "builtins.int", "builtins.int", "builtins.int", "builtins.int", "builtins.int", "builtins.int", "builtins.int", "builtins.int", "builtins.int", "builtins.int", "builtins.int", "builtins.int", "builtins.int", "builtins.int", "builtins.int", "builtins.int", "builtins.int", "builtins.int", "builtins.int", "builtins.int", "builtins.int", "builtins.int", "builtins.int", "builtins.int", "builtins.int", "builtins.int", "builtins.int", "builtins.int", "builtins.int", "builtins.int", "builtins.int", "builtins.int", "builtins.int", "builtins.int", "builtins.int", "builtins.int", "builtins.int", "builtins.int", "builtins.int", "builtins.int", "builtins.int", "builtins.int", "builtins.int", "builtins.int", "builtins.int", "builtins.int", "builtins.int", "builtins.int", "builtins.int", "builtins.int", "builtins.int", "builtins.int", "builtins.int", "builtins.int", "builtins.int", "builtins.int", "builtins.int", "builtins.int", "builtins.int", "builtins.int", "builtins.int", "builtins.int", "builtins.int", "builtins.int", "builtins.int", "builtins.int", "builtins.int", "builtins.int", "builtins.int", "builtins.int", "builtins.int", "builtins.int", "builtins.int", "builtins.int", "builtins.int", "builtins.int", "builtins.int", "builtins.int", "builtins.int"], "partial_fallback": {".class": "Instance", "args": [{".class": "AnyType", "missing_import_name": null, "source_any": null, "type_of_any": 6}], "type_ref": "builtins.tuple"}}}}, "GB2312_SM_MODEL": {".class": "SymbolTableNode", "kind": "Gdef", "node": {".class": "Var", "flags": [], "fullname": "pip._vendor.chardet.mbcssm.GB2312_SM_MODEL", "name": "GB2312_SM_MODEL", "type": {".class": "Instance", "args": ["builtins.str", "builtins.object"], "type_ref": "builtins.dict"}}}, "GB2312_ST": {".class": "SymbolTableNode", "kind": "Gdef", "node": {".class": "Var", "flags": [], "fullname": "pip._vendor.chardet.mbcssm.GB2312_ST", "name": "GB2312_ST", "type": {".class": "TupleType", "implicit": false, "items": ["builtins.int", "builtins.int", "builtins.int", "builtins.int", "builtins.int", "builtins.int", "builtins.int", "builtins.int", "builtins.int", "builtins.int", "builtins.int", "builtins.int", "builtins.int", "builtins.int", "builtins.int", "builtins.int", "builtins.int", "builtins.int", "builtins.int", "builtins.int", "builtins.int", "builtins.int", "builtins.int", "builtins.int", "builtins.int", "builtins.int", "builtins.int", "builtins.int", "builtins.int", "builtins.int", "builtins.int", "builtins.int", "builtins.int", "builtins.int", "builtins.int", "builtins.int", "builtins.int", "builtins.int", "builtins.int", "builtins.int", "builtins.int", "builtins.int", "builtins.int", "builtins.int", "builtins.int", "builtins.int", "builtins.int", "builtins.int"], "partial_fallback": {".class": "Instance", "args": [{".class": "AnyType", "missing_import_name": null, "source_any": null, "type_of_any": 6}], "type_ref": "builtins.tuple"}}}}, "JOHAB_CHAR_LEN_TABLE": {".class": "SymbolTableNode", "kind": "Gdef", "node": {".class": "Var", "flags": [], "fullname": "pip._vendor.chardet.mbcssm.JOHAB_CHAR_LEN_TABLE", "name": "JOHAB_CHAR_LEN_TABLE", "type": {".class": "TupleType", "implicit": false, "items": ["builtins.int", "builtins.int", "builtins.int", "builtins.int", "builtins.int", "builtins.int", "builtins.int", "builtins.int", "builtins.int", "builtins.int"], "partial_fallback": {".class": "Instance", "args": [{".class": "AnyType", "missing_import_name": null, "source_any": null, "type_of_any": 6}], "type_ref": "builtins.tuple"}}}}, "JOHAB_CLS": {".class": "SymbolTableNode", "kind": "Gdef", "node": {".class": "Var", "flags": [], "fullname": "pip._vendor.chardet.mbcssm.JOHAB_CLS", "name": "JOHAB_CLS", "type": {".class": "TupleType", "implicit": false, "items": ["builtins.int", "builtins.int", "builtins.int", "builtins.int", "builtins.int", "builtins.int", "builtins.int", "builtins.int", "builtins.int", "builtins.int", "builtins.int", "builtins.int", "builtins.int", "builtins.int", "builtins.int", "builtins.int", "builtins.int", "builtins.int", "builtins.int", "builtins.int", "builtins.int", "builtins.int", "builtins.int", "builtins.int", "builtins.int", "builtins.int", "builtins.int", "builtins.int", "builtins.int", "builtins.int", "builtins.int", "builtins.int", "builtins.int", "builtins.int", "builtins.int", "builtins.int", "builtins.int", "builtins.int", "builtins.int", "builtins.int", "builtins.int", "builtins.int", "builtins.int", "builtins.int", "builtins.int", "builtins.int", "builtins.int", "builtins.int", "builtins.int", "builtins.int", "builtins.int", "builtins.int", "builtins.int", "builtins.int", "builtins.int", "builtins.int", "builtins.int", "builtins.int", "builtins.int", "builtins.int", "builtins.int", "builtins.int", "builtins.int", "builtins.int", "builtins.int", "builtins.int", "builtins.int", "builtins.int", "builtins.int", "builtins.int", "builtins.int", "builtins.int", "builtins.int", "builtins.int", "builtins.int", "builtins.int", "builtins.int", "builtins.int", "builtins.int", "builtins.int", "builtins.int", "builtins.int", "builtins.int", "builtins.int", "builtins.int", "builtins.int", "builtins.int", "builtins.int", "builtins.int", "builtins.int", "builtins.int", "builtins.int", "builtins.int", "builtins.int", "builtins.int", "builtins.int", "builtins.int", "builtins.int", "builtins.int", "builtins.int", "builtins.int", "builtins.int", "builtins.int", "builtins.int", "builtins.int", "builtins.int", "builtins.int", "builtins.int", "builtins.int", "builtins.int", "builtins.int", "builtins.int", "builtins.int", "builtins.int", "builtins.int", "builtins.int", "builtins.int", "builtins.int", "builtins.int", "builtins.int", "builtins.int", "builtins.int", "builtins.int", "builtins.int", "builtins.int", "builtins.int", "builtins.int", "builtins.int", "builtins.int", "builtins.int", "builtins.int", "builtins.int", "builtins.int", "builtins.int", "builtins.int", "builtins.int", "builtins.int", "builtins.int", "builtins.int", "builtins.int", "builtins.int", "builtins.int", "builtins.int", "builtins.int", "builtins.int", "builtins.int", "builtins.int", "builtins.int", "builtins.int", "builtins.int", "builtins.int", "builtins.int", "builtins.int", "builtins.int", "builtins.int", "builtins.int", "builtins.int", "builtins.int", "builtins.int", "builtins.int", "builtins.int", "builtins.int", "builtins.int", "builtins.int", "builtins.int", "builtins.int", "builtins.int", "builtins.int", "builtins.int", "builtins.int", "builtins.int", "builtins.int", "builtins.int", "builtins.int", "builtins.int", "builtins.int", "builtins.int", "builtins.int", "builtins.int", "builtins.int", "builtins.int", "builtins.int", "builtins.int", "builtins.int", "builtins.int", "builtins.int", "builtins.int", "builtins.int", "builtins.int", "builtins.int", "builtins.int", "builtins.int", "builtins.int", "builtins.int", "builtins.int", "builtins.int", "builtins.int", "builtins.int", "builtins.int", "builtins.int", "builtins.int", "builtins.int", "builtins.int", "builtins.int", "builtins.int", "builtins.int", "builtins.int", "builtins.int", "builtins.int", "builtins.int", "builtins.int", "builtins.int", "builtins.int", "builtins.int", "builtins.int", "builtins.int", "builtins.int", "builtins.int", "builtins.int", "builtins.int", "builtins.int", "builtins.int", "builtins.int", "builtins.int", "builtins.int", "builtins.int", "builtins.int", "builtins.int", "builtins.int", "builtins.int", "builtins.int", "builtins.int", "builtins.int", "builtins.int", "builtins.int", "builtins.int", "builtins.int", "builtins.int", "builtins.int", "builtins.int", "builtins.int", "builtins.int", "builtins.int", "builtins.int", "builtins.int", "builtins.int", "builtins.int", "builtins.int", "builtins.int", "builtins.int", "builtins.int", "builtins.int", "builtins.int", "builtins.int", "builtins.int", "builtins.int"], "partial_fallback": {".class": "Instance", "args": [{".class": "AnyType", "missing_import_name": null, "source_any": null, "type_of_any": 6}], "type_ref": "builtins.tuple"}}}}, "JOHAB_SM_MODEL": {".class": "SymbolTableNode", "kind": "Gdef", "node": {".class": "Var", "flags": [], "fullname": "pip._vendor.chardet.mbcssm.JOHAB_SM_MODEL", "name": "JOHAB_SM_MODEL", "type": {".class": "Instance", "args": ["builtins.str", "builtins.object"], "type_ref": "builtins.dict"}}}, "JOHAB_ST": {".class": "SymbolTableNode", "kind": "Gdef", "node": {".class": "Var", "flags": [], "fullname": "pip._vendor.chardet.mbcssm.JOHAB_ST", "name": "JOHAB_ST", "type": {".class": "TupleType", "implicit": false, "items": ["builtins.int", "builtins.int", "builtins.int", "builtins.int", "builtins.int", "builtins.int", "builtins.int", "builtins.int", "builtins.int", "builtins.int", "builtins.int", "builtins.int", "builtins.int", "builtins.int", "builtins.int", "builtins.int", "builtins.int", "builtins.int", "builtins.int", "builtins.int", "builtins.int", "builtins.int", "builtins.int", "builtins.int", "builtins.int", "builtins.int", "builtins.int", "builtins.int", "builtins.int", "builtins.int", "builtins.int", "builtins.int", "builtins.int", "builtins.int", "builtins.int", "builtins.int", "builtins.int", "builtins.int", "builtins.int", "builtins.int", "builtins.int", "builtins.int", "builtins.int", "builtins.int", "builtins.int", "builtins.int", "builtins.int", "builtins.int", "builtins.int", "builtins.int"], "partial_fallback": {".class": "Instance", "args": [{".class": "AnyType", "missing_import_name": null, "source_any": null, "type_of_any": 6}], "type_ref": "builtins.tuple"}}}}, "MachineState": {".class": "SymbolTableNode", "cross_ref": "pip._vendor.chardet.enums.MachineState", "kind": "Gdef"}, "SJIS_CHAR_LEN_TABLE": {".class": "SymbolTableNode", "kind": "Gdef", "node": {".class": "Var", "flags": [], "fullname": "pip._vendor.chardet.mbcssm.SJIS_CHAR_LEN_TABLE", "name": "SJIS_CHAR_LEN_TABLE", "type": {".class": "TupleType", "implicit": false, "items": ["builtins.int", "builtins.int", "builtins.int", "builtins.int", "builtins.int", "builtins.int"], "partial_fallback": {".class": "Instance", "args": [{".class": "AnyType", "missing_import_name": null, "source_any": null, "type_of_any": 6}], "type_ref": "builtins.tuple"}}}}, "SJIS_CLS": {".class": "SymbolTableNode", "kind": "Gdef", "node": {".class": "Var", "flags": [], "fullname": "pip._vendor.chardet.mbcssm.SJIS_CLS", "name": "SJIS_CLS", "type": {".class": "TupleType", "implicit": false, "items": ["builtins.int", "builtins.int", "builtins.int", "builtins.int", "builtins.int", "builtins.int", "builtins.int", "builtins.int", "builtins.int", "builtins.int", "builtins.int", "builtins.int", "builtins.int", "builtins.int", "builtins.int", "builtins.int", "builtins.int", "builtins.int", "builtins.int", "builtins.int", "builtins.int", "builtins.int", "builtins.int", "builtins.int", "builtins.int", "builtins.int", "builtins.int", "builtins.int", "builtins.int", "builtins.int", "builtins.int", "builtins.int", "builtins.int", "builtins.int", "builtins.int", "builtins.int", "builtins.int", "builtins.int", "builtins.int", "builtins.int", "builtins.int", "builtins.int", "builtins.int", "builtins.int", "builtins.int", "builtins.int", "builtins.int", "builtins.int", "builtins.int", "builtins.int", "builtins.int", "builtins.int", "builtins.int", "builtins.int", "builtins.int", "builtins.int", "builtins.int", "builtins.int", "builtins.int", "builtins.int", "builtins.int", "builtins.int", "builtins.int", "builtins.int", "builtins.int", "builtins.int", "builtins.int", "builtins.int", "builtins.int", "builtins.int", "builtins.int", "builtins.int", "builtins.int", "builtins.int", "builtins.int", "builtins.int", "builtins.int", "builtins.int", "builtins.int", "builtins.int", "builtins.int", "builtins.int", "builtins.int", "builtins.int", "builtins.int", "builtins.int", "builtins.int", "builtins.int", "builtins.int", "builtins.int", "builtins.int", "builtins.int", "builtins.int", "builtins.int", "builtins.int", "builtins.int", "builtins.int", "builtins.int", "builtins.int", "builtins.int", "builtins.int", "builtins.int", "builtins.int", "builtins.int", "builtins.int", "builtins.int", "builtins.int", "builtins.int", "builtins.int", "builtins.int", "builtins.int", "builtins.int", "builtins.int", "builtins.int", "builtins.int", "builtins.int", "builtins.int", "builtins.int", "builtins.int", "builtins.int", "builtins.int", "builtins.int", "builtins.int", "builtins.int", "builtins.int", "builtins.int", "builtins.int", "builtins.int", "builtins.int", "builtins.int", "builtins.int", "builtins.int", "builtins.int", "builtins.int", "builtins.int", "builtins.int", "builtins.int", "builtins.int", "builtins.int", "builtins.int", "builtins.int", "builtins.int", "builtins.int", "builtins.int", "builtins.int", "builtins.int", "builtins.int", "builtins.int", "builtins.int", "builtins.int", "builtins.int", "builtins.int", "builtins.int", "builtins.int", "builtins.int", "builtins.int", "builtins.int", "builtins.int", "builtins.int", "builtins.int", "builtins.int", "builtins.int", "builtins.int", "builtins.int", "builtins.int", "builtins.int", "builtins.int", "builtins.int", "builtins.int", "builtins.int", "builtins.int", "builtins.int", "builtins.int", "builtins.int", "builtins.int", "builtins.int", "builtins.int", "builtins.int", "builtins.int", "builtins.int", "builtins.int", "builtins.int", "builtins.int", "builtins.int", "builtins.int", "builtins.int", "builtins.int", "builtins.int", "builtins.int", "builtins.int", "builtins.int", "builtins.int", "builtins.int", "builtins.int", "builtins.int", "builtins.int", "builtins.int", "builtins.int", "builtins.int", "builtins.int", "builtins.int", "builtins.int", "builtins.int", "builtins.int", "builtins.int", "builtins.int", "builtins.int", "builtins.int", "builtins.int", "builtins.int", "builtins.int", "builtins.int", "builtins.int", "builtins.int", "builtins.int", "builtins.int", "builtins.int", "builtins.int", "builtins.int", "builtins.int", "builtins.int", "builtins.int", "builtins.int", "builtins.int", "builtins.int", "builtins.int", "builtins.int", "builtins.int", "builtins.int", "builtins.int", "builtins.int", "builtins.int", "builtins.int", "builtins.int", "builtins.int", "builtins.int", "builtins.int", "builtins.int", "builtins.int", "builtins.int", "builtins.int", "builtins.int", "builtins.int", "builtins.int", "builtins.int", "builtins.int", "builtins.int", "builtins.int", "builtins.int", "builtins.int", "builtins.int", "builtins.int", "builtins.int", "builtins.int", "builtins.int", "builtins.int"], "partial_fallback": {".class": "Instance", "args": [{".class": "AnyType", "missing_import_name": null, "source_any": null, "type_of_any": 6}], "type_ref": "builtins.tuple"}}}}, "SJIS_SM_MODEL": {".class": "SymbolTableNode", "kind": "Gdef", "node": {".class": "Var", "flags": [], "fullname": "pip._vendor.chardet.mbcssm.SJIS_SM_MODEL", "name": "SJIS_SM_MODEL", "type": {".class": "Instance", "args": ["builtins.str", "builtins.object"], "type_ref": "builtins.dict"}}}, "SJIS_ST": {".class": "SymbolTableNode", "kind": "Gdef", "node": {".class": "Var", "flags": [], "fullname": "pip._vendor.chardet.mbcssm.SJIS_ST", "name": "SJIS_ST", "type": {".class": "TupleType", "implicit": false, "items": ["builtins.int", "builtins.int", "builtins.int", "builtins.int", "builtins.int", "builtins.int", "builtins.int", "builtins.int", "builtins.int", "builtins.int", "builtins.int", "builtins.int", "builtins.int", "builtins.int", "builtins.int", "builtins.int", "builtins.int", "builtins.int", "builtins.int", "builtins.int", "builtins.int", "builtins.int", "builtins.int", "builtins.int"], "partial_fallback": {".class": "Instance", "args": [{".class": "AnyType", "missing_import_name": null, "source_any": null, "type_of_any": 6}], "type_ref": "builtins.tuple"}}}}, "UCS2BE_CHAR_LEN_TABLE": {".class": "SymbolTableNode", "kind": "Gdef", "node": {".class": "Var", "flags": [], "fullname": "pip._vendor.chardet.mbcssm.UCS2BE_CHAR_LEN_TABLE", "name": "UCS2BE_CHAR_LEN_TABLE", "type": {".class": "TupleType", "implicit": false, "items": ["builtins.int", "builtins.int", "builtins.int", "builtins.int", "builtins.int", "builtins.int"], "partial_fallback": {".class": "Instance", "args": [{".class": "AnyType", "missing_import_name": null, "source_any": null, "type_of_any": 6}], "type_ref": "builtins.tuple"}}}}, "UCS2BE_CLS": {".class": "SymbolTableNode", "kind": "Gdef", "node": {".class": "Var", "flags": [], "fullname": "pip._vendor.chardet.mbcssm.UCS2BE_CLS", "name": "UCS2BE_CLS", "type": {".class": "TupleType", "implicit": false, "items": ["builtins.int", "builtins.int", "builtins.int", "builtins.int", "builtins.int", "builtins.int", "builtins.int", "builtins.int", "builtins.int", "builtins.int", "builtins.int", "builtins.int", "builtins.int", "builtins.int", "builtins.int", "builtins.int", "builtins.int", "builtins.int", "builtins.int", "builtins.int", "builtins.int", "builtins.int", "builtins.int", "builtins.int", "builtins.int", "builtins.int", "builtins.int", "builtins.int", "builtins.int", "builtins.int", "builtins.int", "builtins.int", "builtins.int", "builtins.int", "builtins.int", "builtins.int", "builtins.int", "builtins.int", "builtins.int", "builtins.int", "builtins.int", "builtins.int", "builtins.int", "builtins.int", "builtins.int", "builtins.int", "builtins.int", "builtins.int", "builtins.int", "builtins.int", "builtins.int", "builtins.int", "builtins.int", "builtins.int", "builtins.int", "builtins.int", "builtins.int", "builtins.int", "builtins.int", "builtins.int", "builtins.int", "builtins.int", "builtins.int", "builtins.int", "builtins.int", "builtins.int", "builtins.int", "builtins.int", "builtins.int", "builtins.int", "builtins.int", "builtins.int", "builtins.int", "builtins.int", "builtins.int", "builtins.int", "builtins.int", "builtins.int", "builtins.int", "builtins.int", "builtins.int", "builtins.int", "builtins.int", "builtins.int", "builtins.int", "builtins.int", "builtins.int", "builtins.int", "builtins.int", "builtins.int", "builtins.int", "builtins.int", "builtins.int", "builtins.int", "builtins.int", "builtins.int", "builtins.int", "builtins.int", "builtins.int", "builtins.int", "builtins.int", "builtins.int", "builtins.int", "builtins.int", "builtins.int", "builtins.int", "builtins.int", "builtins.int", "builtins.int", "builtins.int", "builtins.int", "builtins.int", "builtins.int", "builtins.int", "builtins.int", "builtins.int", "builtins.int", "builtins.int", "builtins.int", "builtins.int", "builtins.int", "builtins.int", "builtins.int", "builtins.int", "builtins.int", "builtins.int", "builtins.int", "builtins.int", "builtins.int", "builtins.int", "builtins.int", "builtins.int", "builtins.int", "builtins.int", "builtins.int", "builtins.int", "builtins.int", "builtins.int", "builtins.int", "builtins.int", "builtins.int", "builtins.int", "builtins.int", "builtins.int", "builtins.int", "builtins.int", "builtins.int", "builtins.int", "builtins.int", "builtins.int", "builtins.int", "builtins.int", "builtins.int", "builtins.int", "builtins.int", "builtins.int", "builtins.int", "builtins.int", "builtins.int", "builtins.int", "builtins.int", "builtins.int", "builtins.int", "builtins.int", "builtins.int", "builtins.int", "builtins.int", "builtins.int", "builtins.int", "builtins.int", "builtins.int", "builtins.int", "builtins.int", "builtins.int", "builtins.int", "builtins.int", "builtins.int", "builtins.int", "builtins.int", "builtins.int", "builtins.int", "builtins.int", "builtins.int", "builtins.int", "builtins.int", "builtins.int", "builtins.int", "builtins.int", "builtins.int", "builtins.int", "builtins.int", "builtins.int", "builtins.int", "builtins.int", "builtins.int", "builtins.int", "builtins.int", "builtins.int", "builtins.int", "builtins.int", "builtins.int", "builtins.int", "builtins.int", "builtins.int", "builtins.int", "builtins.int", "builtins.int", "builtins.int", "builtins.int", "builtins.int", "builtins.int", "builtins.int", "builtins.int", "builtins.int", "builtins.int", "builtins.int", "builtins.int", "builtins.int", "builtins.int", "builtins.int", "builtins.int", "builtins.int", "builtins.int", "builtins.int", "builtins.int", "builtins.int", "builtins.int", "builtins.int", "builtins.int", "builtins.int", "builtins.int", "builtins.int", "builtins.int", "builtins.int", "builtins.int", "builtins.int", "builtins.int", "builtins.int", "builtins.int", "builtins.int", "builtins.int", "builtins.int", "builtins.int", "builtins.int", "builtins.int", "builtins.int", "builtins.int", "builtins.int", "builtins.int", "builtins.int", "builtins.int", "builtins.int", "builtins.int", "builtins.int", "builtins.int", "builtins.int"], "partial_fallback": {".class": "Instance", "args": [{".class": "AnyType", "missing_import_name": null, "source_any": null, "type_of_any": 6}], "type_ref": "builtins.tuple"}}}}, "UCS2BE_SM_MODEL": {".class": "SymbolTableNode", "kind": "Gdef", "node": {".class": "Var", "flags": [], "fullname": "pip._vendor.chardet.mbcssm.UCS2BE_SM_MODEL", "name": "UCS2BE_SM_MODEL", "type": {".class": "Instance", "args": ["builtins.str", "builtins.object"], "type_ref": "builtins.dict"}}}, "UCS2BE_ST": {".class": "SymbolTableNode", "kind": "Gdef", "node": {".class": "Var", "flags": [], "fullname": "pip._vendor.chardet.mbcssm.UCS2BE_ST", "name": "UCS2BE_ST", "type": {".class": "TupleType", "implicit": false, "items": ["builtins.int", "builtins.int", "builtins.int", "builtins.int", "builtins.int", "builtins.int", "builtins.int", "builtins.int", "builtins.int", "builtins.int", "builtins.int", "builtins.int", "builtins.int", "builtins.int", "builtins.int", "builtins.int", "builtins.int", "builtins.int", "builtins.int", "builtins.int", "builtins.int", "builtins.int", "builtins.int", "builtins.int", "builtins.int", "builtins.int", "builtins.int", "builtins.int", "builtins.int", "builtins.int", "builtins.int", "builtins.int", "builtins.int", "builtins.int", "builtins.int", "builtins.int", "builtins.int", "builtins.int", "builtins.int", "builtins.int", "builtins.int", "builtins.int", "builtins.int", "builtins.int", "builtins.int", "builtins.int", "builtins.int", "builtins.int", "builtins.int", "builtins.int", "builtins.int", "builtins.int", "builtins.int", "builtins.int", "builtins.int", "builtins.int"], "partial_fallback": {".class": "Instance", "args": [{".class": "AnyType", "missing_import_name": null, "source_any": null, "type_of_any": 6}], "type_ref": "builtins.tuple"}}}}, "UCS2LE_CHAR_LEN_TABLE": {".class": "SymbolTableNode", "kind": "Gdef", "node": {".class": "Var", "flags": [], "fullname": "pip._vendor.chardet.mbcssm.UCS2LE_CHAR_LEN_TABLE", "name": "UCS2LE_CHAR_LEN_TABLE", "type": {".class": "TupleType", "implicit": false, "items": ["builtins.int", "builtins.int", "builtins.int", "builtins.int", "builtins.int", "builtins.int"], "partial_fallback": {".class": "Instance", "args": [{".class": "AnyType", "missing_import_name": null, "source_any": null, "type_of_any": 6}], "type_ref": "builtins.tuple"}}}}, "UCS2LE_CLS": {".class": "SymbolTableNode", "kind": "Gdef", "node": {".class": "Var", "flags": [], "fullname": "pip._vendor.chardet.mbcssm.UCS2LE_CLS", "name": "UCS2LE_CLS", "type": {".class": "TupleType", "implicit": false, "items": ["builtins.int", "builtins.int", "builtins.int", "builtins.int", "builtins.int", "builtins.int", "builtins.int", "builtins.int", "builtins.int", "builtins.int", "builtins.int", "builtins.int", "builtins.int", "builtins.int", "builtins.int", "builtins.int", "builtins.int", "builtins.int", "builtins.int", "builtins.int", "builtins.int", "builtins.int", "builtins.int", "builtins.int", "builtins.int", "builtins.int", "builtins.int", "builtins.int", "builtins.int", "builtins.int", "builtins.int", "builtins.int", "builtins.int", "builtins.int", "builtins.int", "builtins.int", "builtins.int", "builtins.int", "builtins.int", "builtins.int", "builtins.int", "builtins.int", "builtins.int", "builtins.int", "builtins.int", "builtins.int", "builtins.int", "builtins.int", "builtins.int", "builtins.int", "builtins.int", "builtins.int", "builtins.int", "builtins.int", "builtins.int", "builtins.int", "builtins.int", "builtins.int", "builtins.int", "builtins.int", "builtins.int", "builtins.int", "builtins.int", "builtins.int", "builtins.int", "builtins.int", "builtins.int", "builtins.int", "builtins.int", "builtins.int", "builtins.int", "builtins.int", "builtins.int", "builtins.int", "builtins.int", "builtins.int", "builtins.int", "builtins.int", "builtins.int", "builtins.int", "builtins.int", "builtins.int", "builtins.int", "builtins.int", "builtins.int", "builtins.int", "builtins.int", "builtins.int", "builtins.int", "builtins.int", "builtins.int", "builtins.int", "builtins.int", "builtins.int", "builtins.int", "builtins.int", "builtins.int", "builtins.int", "builtins.int", "builtins.int", "builtins.int", "builtins.int", "builtins.int", "builtins.int", "builtins.int", "builtins.int", "builtins.int", "builtins.int", "builtins.int", "builtins.int", "builtins.int", "builtins.int", "builtins.int", "builtins.int", "builtins.int", "builtins.int", "builtins.int", "builtins.int", "builtins.int", "builtins.int", "builtins.int", "builtins.int", "builtins.int", "builtins.int", "builtins.int", "builtins.int", "builtins.int", "builtins.int", "builtins.int", "builtins.int", "builtins.int", "builtins.int", "builtins.int", "builtins.int", "builtins.int", "builtins.int", "builtins.int", "builtins.int", "builtins.int", "builtins.int", "builtins.int", "builtins.int", "builtins.int", "builtins.int", "builtins.int", "builtins.int", "builtins.int", "builtins.int", "builtins.int", "builtins.int", "builtins.int", "builtins.int", "builtins.int", "builtins.int", "builtins.int", "builtins.int", "builtins.int", "builtins.int", "builtins.int", "builtins.int", "builtins.int", "builtins.int", "builtins.int", "builtins.int", "builtins.int", "builtins.int", "builtins.int", "builtins.int", "builtins.int", "builtins.int", "builtins.int", "builtins.int", "builtins.int", "builtins.int", "builtins.int", "builtins.int", "builtins.int", "builtins.int", "builtins.int", "builtins.int", "builtins.int", "builtins.int", "builtins.int", "builtins.int", "builtins.int", "builtins.int", "builtins.int", "builtins.int", "builtins.int", "builtins.int", "builtins.int", "builtins.int", "builtins.int", "builtins.int", "builtins.int", "builtins.int", "builtins.int", "builtins.int", "builtins.int", "builtins.int", "builtins.int", "builtins.int", "builtins.int", "builtins.int", "builtins.int", "builtins.int", "builtins.int", "builtins.int", "builtins.int", "builtins.int", "builtins.int", "builtins.int", "builtins.int", "builtins.int", "builtins.int", "builtins.int", "builtins.int", "builtins.int", "builtins.int", "builtins.int", "builtins.int", "builtins.int", "builtins.int", "builtins.int", "builtins.int", "builtins.int", "builtins.int", "builtins.int", "builtins.int", "builtins.int", "builtins.int", "builtins.int", "builtins.int", "builtins.int", "builtins.int", "builtins.int", "builtins.int", "builtins.int", "builtins.int", "builtins.int", "builtins.int", "builtins.int", "builtins.int", "builtins.int", "builtins.int", "builtins.int", "builtins.int", "builtins.int", "builtins.int", "builtins.int", "builtins.int", "builtins.int", "builtins.int", "builtins.int", "builtins.int", "builtins.int"], "partial_fallback": {".class": "Instance", "args": [{".class": "AnyType", "missing_import_name": null, "source_any": null, "type_of_any": 6}], "type_ref": "builtins.tuple"}}}}, "UCS2LE_SM_MODEL": {".class": "SymbolTableNode", "kind": "Gdef", "node": {".class": "Var", "flags": [], "fullname": "pip._vendor.chardet.mbcssm.UCS2LE_SM_MODEL", "name": "UCS2LE_SM_MODEL", "type": {".class": "Instance", "args": ["builtins.str", "builtins.object"], "type_ref": "builtins.dict"}}}, "UCS2LE_ST": {".class": "SymbolTableNode", "kind": "Gdef", "node": {".class": "Var", "flags": [], "fullname": "pip._vendor.chardet.mbcssm.UCS2LE_ST", "name": "UCS2LE_ST", "type": {".class": "TupleType", "implicit": false, "items": ["builtins.int", "builtins.int", "builtins.int", "builtins.int", "builtins.int", "builtins.int", "builtins.int", "builtins.int", "builtins.int", "builtins.int", "builtins.int", "builtins.int", "builtins.int", "builtins.int", "builtins.int", "builtins.int", "builtins.int", "builtins.int", "builtins.int", "builtins.int", "builtins.int", "builtins.int", "builtins.int", "builtins.int", "builtins.int", "builtins.int", "builtins.int", "builtins.int", "builtins.int", "builtins.int", "builtins.int", "builtins.int", "builtins.int", "builtins.int", "builtins.int", "builtins.int", "builtins.int", "builtins.int", "builtins.int", "builtins.int", "builtins.int", "builtins.int", "builtins.int", "builtins.int", "builtins.int", "builtins.int", "builtins.int", "builtins.int", "builtins.int", "builtins.int", "builtins.int", "builtins.int", "builtins.int", "builtins.int", "builtins.int", "builtins.int"], "partial_fallback": {".class": "Instance", "args": [{".class": "AnyType", "missing_import_name": null, "source_any": null, "type_of_any": 6}], "type_ref": "builtins.tuple"}}}}, "UTF8_CHAR_LEN_TABLE": {".class": "SymbolTableNode", "kind": "Gdef", "node": {".class": "Var", "flags": [], "fullname": "pip._vendor.chardet.mbcssm.UTF8_CHAR_LEN_TABLE", "name": "UTF8_CHAR_LEN_TABLE", "type": {".class": "TupleType", "implicit": false, "items": ["builtins.int", "builtins.int", "builtins.int", "builtins.int", "builtins.int", "builtins.int", "builtins.int", "builtins.int", "builtins.int", "builtins.int", "builtins.int", "builtins.int", "builtins.int", "builtins.int", "builtins.int", "builtins.int"], "partial_fallback": {".class": "Instance", "args": [{".class": "AnyType", "missing_import_name": null, "source_any": null, "type_of_any": 6}], "type_ref": "builtins.tuple"}}}}, "UTF8_CLS": {".class": "SymbolTableNode", "kind": "Gdef", "node": {".class": "Var", "flags": [], "fullname": "pip._vendor.chardet.mbcssm.UTF8_CLS", "name": "UTF8_CLS", "type": {".class": "TupleType", "implicit": false, "items": ["builtins.int", "builtins.int", "builtins.int", "builtins.int", "builtins.int", "builtins.int", "builtins.int", "builtins.int", "builtins.int", "builtins.int", "builtins.int", "builtins.int", "builtins.int", "builtins.int", "builtins.int", "builtins.int", "builtins.int", "builtins.int", "builtins.int", "builtins.int", "builtins.int", "builtins.int", "builtins.int", "builtins.int", "builtins.int", "builtins.int", "builtins.int", "builtins.int", "builtins.int", "builtins.int", "builtins.int", "builtins.int", "builtins.int", "builtins.int", "builtins.int", "builtins.int", "builtins.int", "builtins.int", "builtins.int", "builtins.int", "builtins.int", "builtins.int", "builtins.int", "builtins.int", "builtins.int", "builtins.int", "builtins.int", "builtins.int", "builtins.int", "builtins.int", "builtins.int", "builtins.int", "builtins.int", "builtins.int", "builtins.int", "builtins.int", "builtins.int", "builtins.int", "builtins.int", "builtins.int", "builtins.int", "builtins.int", "builtins.int", "builtins.int", "builtins.int", "builtins.int", "builtins.int", "builtins.int", "builtins.int", "builtins.int", "builtins.int", "builtins.int", "builtins.int", "builtins.int", "builtins.int", "builtins.int", "builtins.int", "builtins.int", "builtins.int", "builtins.int", "builtins.int", "builtins.int", "builtins.int", "builtins.int", "builtins.int", "builtins.int", "builtins.int", "builtins.int", "builtins.int", "builtins.int", "builtins.int", "builtins.int", "builtins.int", "builtins.int", "builtins.int", "builtins.int", "builtins.int", "builtins.int", "builtins.int", "builtins.int", "builtins.int", "builtins.int", "builtins.int", "builtins.int", "builtins.int", "builtins.int", "builtins.int", "builtins.int", "builtins.int", "builtins.int", "builtins.int", "builtins.int", "builtins.int", "builtins.int", "builtins.int", "builtins.int", "builtins.int", "builtins.int", "builtins.int", "builtins.int", "builtins.int", "builtins.int", "builtins.int", "builtins.int", "builtins.int", "builtins.int", "builtins.int", "builtins.int", "builtins.int", "builtins.int", "builtins.int", "builtins.int", "builtins.int", "builtins.int", "builtins.int", "builtins.int", "builtins.int", "builtins.int", "builtins.int", "builtins.int", "builtins.int", "builtins.int", "builtins.int", "builtins.int", "builtins.int", "builtins.int", "builtins.int", "builtins.int", "builtins.int", "builtins.int", "builtins.int", "builtins.int", "builtins.int", "builtins.int", "builtins.int", "builtins.int", "builtins.int", "builtins.int", "builtins.int", "builtins.int", "builtins.int", "builtins.int", "builtins.int", "builtins.int", "builtins.int", "builtins.int", "builtins.int", "builtins.int", "builtins.int", "builtins.int", "builtins.int", "builtins.int", "builtins.int", "builtins.int", "builtins.int", "builtins.int", "builtins.int", "builtins.int", "builtins.int", "builtins.int", "builtins.int", "builtins.int", "builtins.int", "builtins.int", "builtins.int", "builtins.int", "builtins.int", "builtins.int", "builtins.int", "builtins.int", "builtins.int", "builtins.int", "builtins.int", "builtins.int", "builtins.int", "builtins.int", "builtins.int", "builtins.int", "builtins.int", "builtins.int", "builtins.int", "builtins.int", "builtins.int", "builtins.int", "builtins.int", "builtins.int", "builtins.int", "builtins.int", "builtins.int", "builtins.int", "builtins.int", "builtins.int", "builtins.int", "builtins.int", "builtins.int", "builtins.int", "builtins.int", "builtins.int", "builtins.int", "builtins.int", "builtins.int", "builtins.int", "builtins.int", "builtins.int", "builtins.int", "builtins.int", "builtins.int", "builtins.int", "builtins.int", "builtins.int", "builtins.int", "builtins.int", "builtins.int", "builtins.int", "builtins.int", "builtins.int", "builtins.int", "builtins.int", "builtins.int", "builtins.int", "builtins.int", "builtins.int", "builtins.int", "builtins.int", "builtins.int", "builtins.int", "builtins.int", "builtins.int", "builtins.int", "builtins.int", "builtins.int", "builtins.int", "builtins.int", "builtins.int", "builtins.int", "builtins.int"], "partial_fallback": {".class": "Instance", "args": [{".class": "AnyType", "missing_import_name": null, "source_any": null, "type_of_any": 6}], "type_ref": "builtins.tuple"}}}}, "UTF8_SM_MODEL": {".class": "SymbolTableNode", "kind": "Gdef", "node": {".class": "Var", "flags": [], "fullname": "pip._vendor.chardet.mbcssm.UTF8_SM_MODEL", "name": "UTF8_SM_MODEL", "type": {".class": "Instance", "args": ["builtins.str", "builtins.object"], "type_ref": "builtins.dict"}}}, "UTF8_ST": {".class": "SymbolTableNode", "kind": "Gdef", "node": {".class": "Var", "flags": [], "fullname": "pip._vendor.chardet.mbcssm.UTF8_ST", "name": "UTF8_ST", "type": {".class": "TupleType", "implicit": false, "items": ["builtins.int", "builtins.int", "builtins.int", "builtins.int", "builtins.int", "builtins.int", "builtins.int", "builtins.int", "builtins.int", "builtins.int", "builtins.int", "builtins.int", "builtins.int", "builtins.int", "builtins.int", "builtins.int", "builtins.int", "builtins.int", "builtins.int", "builtins.int", "builtins.int", "builtins.int", "builtins.int", "builtins.int", "builtins.int", "builtins.int", "builtins.int", "builtins.int", "builtins.int", "builtins.int", "builtins.int", "builtins.int", "builtins.int", "builtins.int", "builtins.int", "builtins.int", "builtins.int", "builtins.int", "builtins.int", "builtins.int", "builtins.int", "builtins.int", "builtins.int", "builtins.int", "builtins.int", "builtins.int", "builtins.int", "builtins.int", "builtins.int", "builtins.int", "builtins.int", "builtins.int", "builtins.int", "builtins.int", "builtins.int", "builtins.int", "builtins.int", "builtins.int", "builtins.int", "builtins.int", "builtins.int", "builtins.int", "builtins.int", "builtins.int", "builtins.int", "builtins.int", "builtins.int", "builtins.int", "builtins.int", "builtins.int", "builtins.int", "builtins.int", "builtins.int", "builtins.int", "builtins.int", "builtins.int", "builtins.int", "builtins.int", "builtins.int", "builtins.int", "builtins.int", "builtins.int", "builtins.int", "builtins.int", "builtins.int", "builtins.int", "builtins.int", "builtins.int", "builtins.int", "builtins.int", "builtins.int", "builtins.int", "builtins.int", "builtins.int", "builtins.int", "builtins.int", "builtins.int", "builtins.int", "builtins.int", "builtins.int", "builtins.int", "builtins.int", "builtins.int", "builtins.int", "builtins.int", "builtins.int", "builtins.int", "builtins.int", "builtins.int", "builtins.int", "builtins.int", "builtins.int", "builtins.int", "builtins.int", "builtins.int", "builtins.int", "builtins.int", "builtins.int", "builtins.int", "builtins.int", "builtins.int", "builtins.int", "builtins.int", "builtins.int", "builtins.int", "builtins.int", "builtins.int", "builtins.int", "builtins.int", "builtins.int", "builtins.int", "builtins.int", "builtins.int", "builtins.int", "builtins.int", "builtins.int", "builtins.int", "builtins.int", "builtins.int", "builtins.int", "builtins.int", "builtins.int", "builtins.int", "builtins.int", "builtins.int", "builtins.int", "builtins.int", "builtins.int", "builtins.int", "builtins.int", "builtins.int", "builtins.int", "builtins.int", "builtins.int", "builtins.int", "builtins.int", "builtins.int", "builtins.int", "builtins.int", "builtins.int", "builtins.int", "builtins.int", "builtins.int", "builtins.int", "builtins.int", "builtins.int", "builtins.int", "builtins.int", "builtins.int", "builtins.int", "builtins.int", "builtins.int", "builtins.int", "builtins.int", "builtins.int", "builtins.int", "builtins.int", "builtins.int", "builtins.int", "builtins.int", "builtins.int", "builtins.int", "builtins.int", "builtins.int", "builtins.int", "builtins.int", "builtins.int", "builtins.int", "builtins.int", "builtins.int", "builtins.int", "builtins.int", "builtins.int", "builtins.int", "builtins.int", "builtins.int", "builtins.int", "builtins.int", "builtins.int", "builtins.int", "builtins.int", "builtins.int", "builtins.int", "builtins.int", "builtins.int", "builtins.int", "builtins.int", "builtins.int"], "partial_fallback": {".class": "Instance", "args": [{".class": "AnyType", "missing_import_name": null, "source_any": null, "type_of_any": 6}], "type_ref": "builtins.tuple"}}}}, "__doc__": {".class": "SymbolTableNode", "kind": "Gdef", "node": {".class": "Var", "flags": ["is_ready"], "fullname": "pip._vendor.chardet.mbcssm.__doc__", "name": "__doc__", "type": "builtins.str"}}, "__file__": {".class": "SymbolTableNode", "kind": "Gdef", "node": {".class": "Var", "flags": ["is_ready"], "fullname": "pip._vendor.chardet.mbcssm.__file__", "name": "__file__", "type": "builtins.str"}}, "__name__": {".class": "SymbolTableNode", "kind": "Gdef", "node": {".class": "Var", "flags": ["is_ready"], "fullname": "pip._vendor.chardet.mbcssm.__name__", "name": "__name__", "type": "builtins.str"}}, "__package__": {".class": "SymbolTableNode", "kind": "Gdef", "node": {".class": "Var", "flags": ["is_ready"], "fullname": "pip._vendor.chardet.mbcssm.__package__", "name": "__package__", "type": "builtins.str"}}}, "path": "C:\\Users\\antho\\anaconda3\\lib\\site-packages\\pip\\_vendor\\chardet\\mbcssm.py"}